Metadata-Version: 2.1
Name: desktop-wrapper
Version: 0.0.12
Summary: A Python package to Build Python Desktop applications using React as GUI.
Author-email: Daniel Rodriguez <danrodcastillo1994@gmail.com>
Project-URL: Homepage, https://github.com/Danucas/desktop_wrapper
Keywords: interface,gui,react,Desktop,Python
Classifier: Programming Language :: Python :: 3
Classifier: License :: OSI Approved :: MIT License
Classifier: Operating System :: OS Independent
Requires-Python: >=3.8
Requires-Dist: Flask==3.0.0
Requires-Dist: Flask-Cors==4.0.0
Requires-Dist: pywebview==4.4.1
Requires-Dist: requests==2.31.0
